seq.v
module seq(
    input x,         // Input signal x
    input clk,       // Clock signal
    input clr,       // Asynchronous clear signal
    output reg z     // Output signal z
);

    // State encoding
    parameter S0 = 0, S1 = 1, S2 = 2, S3 = 3, S4 = 4, S5 = 5;
    reg [2:0] PS, NS;  // PS: Present State, NS: Next State

    // State transition logic (synchronous with asynchronous clear)
    always @(posedge clk or posedge clr) begin
        if (clr)
            PS <= S0;    // Reset to initial state S0 when clear is active
        else
            PS <= NS;    // Transition to next state
    end

    // Next state logic (combinational)
    always @(*) begin
        case (PS)
            S0: NS = x ? S1 : S0;  // If x is 1, go to S1, otherwise stay in S0
            S1: NS = x ? S1 : S2;  // If x is 1, stay in S1, otherwise go to S2
            S2: NS = x ? S3 : S0;  // If x is 1, go to S3, otherwise go to S0
            S3: NS = x ? S1 : S4;  // If x is 1, go to S1, otherwise go to S4
            S4: NS = x ? S5 : S0;  // If x is 1, go to S5, otherwise go to S0
            S5: NS = x ? S1 : S4;  // If x is 1, go to S1, otherwise stay in S4
            default: NS = S0;      // Default state is S0
        endcase
    end

    // Output logic (synchronous with asynchronous clear)
    always @(posedge clk or posedge clr) begin
        if (clr)
            z <= 0;    // Reset output z when clear is active
        else begin
            case (PS)
                S0: z <= 0;  // Output z is 0 in state S0
                S1: z <= 0;  // Output z is 0 in state S1
                S2: z <= 0;  // Output z is 0 in state S2
                S3: z <= 0;  // Output z is 0 in state S3
                S4: z <= 0;  // Output z is 0 in state S4
                S5: z <= x ? 0 : 1;  // Output z is 0 if x is 1, otherwise 1 in state S5
                default: z <= 0;  // Default output is 0
            endcase
        end
    end
endmodule

seq_tb.v
module seq_tb();
    // Declare testbench signals
    reg x, clk, clr;    // Input signals for the DUT (Device Under Test)
    wire z;             // Output signal from the DUT

    // Instantiate the DUT
    seq DUT(.x(x), .clk(clk), .z(z), .clr(clr));

    // Initial block for initializing signals and controlling the test sequence
    initial begin
        clk = 1'b0;     // Initialize clock to 0
        clr = 1'b1;     // Initialize clear to 1 (active)
        #15 clr = 1'b0; // Deactivate clear after 15 time units
    end

    // Clock generation logic: toggle the clock every 5 time units
    always #5 clk = ~clk;

    // Initial block for test stimulus and waveform generation
    initial begin
        $dumpfile("example.vcd");   // Specify the name of the VCD file for waveform dumping
        $dumpvars(0, seq_tb);       // Dump all variables in the testbench
        $monitor($time, " x=%2b, z=%2b", x, z); // Monitor and display changes in x and z

        // Apply test stimulus
        #12 x = 1'b1; #10 x = 1'b0; // Apply x = 1, then x = 0 after 10 time units
        #10 x = 1'b1; #10 x = 1'b0; // Repeat the process to cover various state transitions
        #10 x = 1'b1; #10 x = 1'b0;
        #10 x = 1'b1; #10 x = 1'b0;
        #10 x = 1'b1; #10 x = 1'b0;
        #10 x = 1'b1; #10 x = 1'b0;
        #10 x = 1'b1; #10 x = 1'b0;
        #10 x = 1'b1; #10 x = 1'b0;
        #5 $finish; // End the simulation
    end
endmodule

example.vcd
$date
	Sun Jun 30 02:02:04 2024
$end
$version
	Icarus Verilog
$end
$timescale
	1s
$end
$scope module seq_tb $end
$var wire 1 ! z $end
$var reg 1 " clk $end
$var reg 1 # clr $end
$var reg 1 $ x $end
$scope module DUT $end
$var wire 1 " clk $end
$var wire 1 # clr $end
$var wire 1 $ x $end
$var parameter 32 % S0 $end
$var parameter 32 & S1 $end
$var parameter 32 ' S2 $end
$var parameter 32 ( S3 $end
$var parameter 32 ) S4 $end
$var parameter 32 * S5 $end
$var reg 3 + NS [2:0] $end
$var reg 3 , PS [2:0] $end
$var reg 1 ! z $end
$upscope $end
$upscope $end
$enddefinitions $end
$comment Show the parameter values. $end
$dumpall
b101 *
b100 )
b11 (
b10 '
b1 &
b0 %
$end
#0
$dumpvars
b0 ,
b0x +
x$
1#
0"
0!
$end
#5
1"
#10
0"
#12
b1 +
1$
#15
b1 ,
1"
0#
#20
0"
#22
b10 +
0$
#25
b0 +
b10 ,
1"
#30
0"
#32
b11 +
1$
#35
b1 +
b11 ,
1"
#40
0"
#42
b100 +
0$
#45
b0 +
b100 ,
1"
#50
0"
#52
b101 +
1$
#55
b1 +
b101 ,
1"
#60
0"
#62
b100 +
0$
#65
b0 +
1!
b100 ,
1"
#70
0"
#72
b101 +
1$
#75
b1 +
b101 ,
0!
1"
#80
0"
#82
b100 +
0$
#85
b0 +
1!
b100 ,
1"
#90
0"
#92
b101 +
1$
#95
b1 +
b101 ,
0!
1"
#100
0"
#102
b100 +
0$
#105
b0 +
1!
b100 ,
1"
#110
0"
#112
b101 +
1$
#115
b1 +
b101 ,
0!
1"
#120
0"
#122
b100 +
0$
#125
b0 +
1!
b100 ,
1"
#130
0"
#132
b101 +
1$
#135
b1 +
b101 ,
0!
1"
#140
0"
#142
b100 +
0$
#145
b0 +
1!
b100 ,
1"
#150
0"
#152
b101 +
1$
#155
b1 +
b101 ,
0!
1"
#160
0"
#162
b100 +
0$
#165
b0 +
1!
b100 ,
1"
